py_maui-0.1.3.dist-info/METADATA
py_maui-0.1.3.dist-info/WHEEL
py_maui-0.1.3.dist-info/license_files/LICENSE
py_maui.libs/libudev-a3a72e90.so.1
py_maui.libs/libcap-e72d96f5.so.2
py_maui.libs/libusb-1-ac37e521.0.so.0
py_maui/__init__.py
py_maui/__init__.pyi
py_maui/py.typed
py_maui/py_maui.cpython-311-x86_64-linux-gnu.so
py_maui-0.1.3.dist-info/RECORD
